{"appearance":{"foregroundColor":"#1f2328","backgroundColor":"#ffffff","tintColor":"#1b7c83","palette":{"0":"#1f2328","1":"#cf222e","2":"#1a7f37","3":"#9a6700","4":"#0969da","5":"#8250df","6":"#1b7c83","7":"#6e7781","8":"#57606a","9":"#a40e26","10":"#116329","11":"#633c01","12":"#0550ae","13":"#8250df","14":"#116b74","15":"#24292f"},"colorScheme":"light","colorSchemeContrast":"increased","source":"override"},"theme":{"foreground":"#1f2328","background":"#ffffff","tint":"#1b7c83","separator":"#57606a","selection":"#c8ddff","placeholder":"#57606a","link":"#0969da","fill":"#f6f8fa","windowBackground":"#ffffff","success":"#1a7f37","warning":"#9a6700","danger":"#cf222e","info":"#1b7c83","muted":"#57606a"}}
